{
   "minVersion": "0.1",
   "headerImage": "",
   "tintColor": "#2cb1be",
   "tabs": [
      {
         "tabname": "Details",
         "views": [
            
            {
               "markdown": "<b>CCToggle blocking Ads & harmful sites</b><br><br>When this toggle is enabled, it blocks Ads & harmful sites in all apps. <br><br><font color='red'><b>Requires</b></font><br>LetMeBlock (<a href='https://poomsmart.github.io/repo'>https://poomsmart.github.io/repo</a>)<br><br><b>Thanks</b><br>StevenBlack<br>280blocker.net<br>hosts2ch",
               "useSpacing": true,
               "class": "DepictionMarkdownView"
            },
            {
               "class": "DepictionSeparatorView"
            },
            {
               "title": "Latest Version",
               "class": "DepictionHeaderView"
            },
            {
               "class":"BeginingOfTable"
            },
            {
               "title": "Version",
               "text": "0.0.4",
               "class": "DepictionTableTextView"
            },
            {
               "title": "Released",
               "text": "2019/05/19",
               "class": "DepictionTableTextView"
            },
            {
               "title": "Compatibility",
               "text": "iOS 12.0 or later (arm64/arm64e)",
               "class": "DepictionTableTextView"
            },
            {
               "title": "Price",
               "text": "Free",
               "class": "DepictionTableTextView"
            },
            {
               "title": "Developer",
               "text": "PetitStrawberry",
               "class": "DepictionTableTextView"
            },
            {
               "class": "EndOfTable"
            },
            {
               "title": "Contact Support",
               "action": "https://twitter.com/petitstb",
               "class": "DepictionTableButtonView"
            },
            {
               "spacing": 16,
               "class": "DepictionSpacerView"
            },
            {
               "spacing": 20,
               "class": "DepictionSpacerView"
            }
         ],
         "class": "DepictionStackView"
      },
      {
         "tabname": "Changelog",
         "views": [
            {
               "title": "0.0.4",
               "useBoldText": true,
               "useBottomMargin": true,
               "class": "DepictionSubheaderView"
            },
            {
               "markdown": "<div id='inline'><ul><li>Small bug fix</li></ul></div>",
               "useSpacing": false,
               "class": "DepictionMarkdownView"
            },
            {
               "markdown": "<small style=\"color: #999; margin-top: -8px;\">Released 2019/05/19</small>",
               "useRawFormat": true,
               "class": "DepictionMarkdownView"
            },
            {
              "class": "DepictionSeparatorView"
            },
            {
               "title": "0.0.3",
               "useBoldText": true,
               "useBottomMargin": true,
               "class": "DepictionSubheaderView"
            },
            {
               "markdown": "<ul><li>arm64e support</li><li>Chimera support</li><li>Change package identifier</li></ul>",
               "useSpacing": false,
               "class": "DepictionMarkdownView"
            },
            {
               "markdown": "<small style=\"color: #999; margin-top: -8px;\">Released 2019/05/19</small>",
               "useRawFormat": true,
               "class": "DepictionMarkdownView"
            },
            {
              "class": "DepictionSeparatorView"
            },
            {
               "title": "0.0.2",
               "useBoldText": true,
               "useBottomMargin": true,
               "class": "DepictionSubheaderView"
            },
            {
               "markdown": "<ul><li>Fixed not working for some users</li></ul>",
               "useSpacing": false,
               "class": "DepictionMarkdownView"
            },
            {
               "markdown": "<small style=\"color: #999; margin-top: -8px;\">Released 2019/03/17</small>",
               "useRawFormat": true,
               "class": "DepictionMarkdownView"
            },
            {
              "class": "DepictionSeparatorView"
            },
            {
               "title": "0.0.1",
               "useBoldText": true,
               "useBottomMargin": true,
               "class": "DepictionSubheaderView"
            },
            {
               "markdown": "<ul><li>Initial Release</li></ul>",
               "useSpacing": false,
               "class": "DepictionMarkdownView"
            },
            {
               "markdown": "<small style=\"color: #999; margin-top: -8px;\">Released 2019/03/01</small>",
               "useRawFormat": true,
               "class": "DepictionMarkdownView"
            }
         ],
         "class": "DepictionStackView"
      }
   ],
   "class": "DepictionTabView"
}
